{"admin": {"hash": "$2b$12$vm1/aVYwBI66k/vohhx5L.a70BFlvwrx1r8ggTYnNZ0zbRBQuPXIu", "plan": "Enterprise"}, "tester1": {"hash": "$2b$12$/S/LclWGtjT.ItbYsKPnceVFidsHFCPWlspW2uLLxcdg940T.WUiu", "plan": "Free"}, "user2026": {"hash": "$2b$12$NmcMCDhJ8Ne8b20a/nDSTuylEnSzErQFY2jd3oEezhxKMl/rGfdyW", "plan": "Free"}, "tester123": {"hash": "$2b$12$.KZ3VIAsbjsGTdhiQH/ktunzsEjAgh8r3MttC7SEapHgu5824qQ2q", "plan": "Free"}, "admin_demo": {"hash": "$2b$12$UPhzc1P/CkSd50iBkwQ7N.IlAfre3CJd4o5r0COT8C9ZStLnOyz/C", "plan": "Free"}}